api_entreprise/__init__.py
api_entreprise/api.py
api_entreprise/cli.py
api_entreprise/exceptions.py
api_entreprise/handlers.py
api_entreprise/models/__init__.py
api_entreprise/models/certification_qualibat.py
api_entreprise/models/certification_rge.py
api_entreprise/models/chiffre_daffaires.py
api_entreprise/models/config.py
api_entreprise/models/context_info.py
api_entreprise/models/donnees_etablissement.py
api_entreprise/models/errors.py
api_entreprise/models/healthcheck_status.py
api_entreprise/models/numero_tva.py
api_entreprise/utils/__init__.py
api_entreprise/utils/metaclasses.py
api_entreprise/utils/url.py
api_entreprise-3.7.2.dist-info/licenses/LICENSE
api_entreprise-3.7.2.dist-info/METADATA
api_entreprise-3.7.2.dist-info/WHEEL
api_entreprise-3.7.2.dist-info/entry_points.txt
api_entreprise-3.7.2.dist-info/top_level.txt
api_entreprise-3.7.2.dist-info/RECORD
