Metadata-Version: 2.4
Name: api-entreprise
Version: 3.7.2
Project-URL: Repository, https://github.com/SIB-rennes/api-entreprise
Requires-Python: >=3.11
License-File: LICENSE
Requires-Dist: requests~=2.28
Requires-Dist: pyrate-limiter~=2.10
Requires-Dist: redis~=4.3
Requires-Dist: marshmallow~=3.19
Requires-Dist: marshmallow-dataclass~=8.5
Provides-Extra: dev
Requires-Dist: build; extra == "dev"
Requires-Dist: black; extra == "dev"
Requires-Dist: mypy; extra == "dev"
Requires-Dist: twine; extra == "dev"
Requires-Dist: pre-commit; extra == "dev"
Requires-Dist: types-requests; extra == "dev"
Provides-Extra: test
Requires-Dist: pytest; extra == "test"
Requires-Dist: vcrpy>=4.2; extra == "test"
Dynamic: license-file
